ccx_keys/__init__.py
ccx_keys/key.py
ccx_keys/locator.py
edx_ccx_keys-2.0.2.dist-info/AUTHORS
edx_ccx_keys-2.0.2.dist-info/LICENSE
edx_ccx_keys-2.0.2.dist-info/METADATA
edx_ccx_keys-2.0.2.dist-info/WHEEL
edx_ccx_keys-2.0.2.dist-info/entry_points.txt
edx_ccx_keys-2.0.2.dist-info/top_level.txt
edx_ccx_keys-2.0.2.dist-info/RECORD
