Metadata-Version: 2.1
Name: edx-ccx-keys
Version: 2.0.2
Summary: Opaque key support custom courses on edX
Home-page: https://github.com/openedx/ccx-keys
Author: edX
Author-email: oscm@edx.org
License: AGPL
Classifier: Development Status :: 5 - Production/Stable
Classifier: Environment :: Web Environment
Classifier: Intended Audience :: Developers
Classifier: License :: OSI Approved :: GNU Affero General Public License v3
Classifier: Operating System :: OS Independent
Classifier: Programming Language :: Python
Classifier: Programming Language :: Python :: 3
Classifier: Programming Language :: Python :: 3.12
License-File: LICENSE
License-File: AUTHORS
Requires-Dist: edx-opaque-keys>=2.0.0
Requires-Dist: six>=1.10.0
